wjj/__init__.py
wjj/file/__init__.py
wjj/file/op.py
wjj/path/__init__.py
wjj/path/op.py
wjj-0.1.4.2.dist-info/LICENSE
wjj-0.1.4.2.dist-info/METADATA
wjj-0.1.4.2.dist-info/WHEEL
wjj-0.1.4.2.dist-info/top_level.txt
wjj-0.1.4.2.dist-info/RECORD
